kclasses/__init__.py
kclasses/kdict.py
kclasses/klist.py
kclasses/ktuple.py
kclasses-0.1.4.dist-info/licenses/LICENSE
kclasses-0.1.4.dist-info/METADATA
kclasses-0.1.4.dist-info/WHEEL
kclasses-0.1.4.dist-info/top_level.txt
kclasses-0.1.4.dist-info/RECORD
