Metadata-Version: 2.4
Name: kclasses
Version: 0.1.4
Summary: Extensions of built-in Python classes
Author-email: KeVeon White <keveonwhite@gmail.com>
License-Expression: Unlicense
Project-URL: Homepage, https://github.com/AMS0x2A/KClasses
Project-URL: Issues, https://github.com/AMS0x2A/KClasses/issues
Classifier: Operating System :: OS Independent
Classifier: Programming Language :: Python :: 3
Requires-Python: >=3.10
License-File: LICENSE
Dynamic: license-file
